easybase/__init__.py
easybase/main.py
easybase_python-1.0.6.dist-info/LICENSE
easybase_python-1.0.6.dist-info/METADATA
easybase_python-1.0.6.dist-info/WHEEL
easybase_python-1.0.6.dist-info/top_level.txt
easybase_python-1.0.6.dist-info/RECORD
