Metadata-Version: 2.1
Name: easybase-python
Version: 1.0.6
Summary: Python package for use with EasyBase.io
Home-page: https://github.com/easybase/easybase-python
Author: EasyBase
Author-email: hello@easybase.io
License: UNKNOWN
Platform: UNKNOWN
Classifier: Programming Language :: Python :: 3
Classifier: License :: OSI Approved :: MIT License
Classifier: Operating System :: OS Independent
Classifier: Intended Audience :: Developers
Classifier: Natural Language :: English
Requires-Python: >=3.4, !=3.0.*, !=3.1.*, !=3.2.*, !=3.3.*, !=3.4.*
